sigal/__init__.py
sigal/__main__.py
sigal/gallery.py
sigal/image.py
sigal/log.py
sigal/settings.py
sigal/signals.py
sigal/utils.py
sigal/version.py
sigal/video.py
sigal/writer.py
sigal/plugins/__init__.py
sigal/plugins/adjust.py
sigal/plugins/compress_assets.py
sigal/plugins/copyright.py
sigal/plugins/extended_caching.py
sigal/plugins/feeds.py
sigal/plugins/media_page.py
sigal/plugins/nomedia.py
sigal/plugins/nonmedia_files.py
sigal/plugins/titleregexp.py
sigal/plugins/watermark.py
sigal/plugins/zip_gallery.py
sigal/plugins/encrypt/__init__.py
sigal/plugins/encrypt/encrypt.py
sigal/plugins/encrypt/endec.py
sigal/plugins/encrypt/static/decrypt.js
sigal/plugins/encrypt/static/keycheck.txt
sigal/plugins/encrypt/static/sw.js
sigal/templates/sigal.conf.py
sigal/themes/colorbox/static/css/colorbox.css
sigal/themes/colorbox/static/css/skeleton.css
sigal/themes/colorbox/static/css/style.css
sigal/themes/colorbox/static/images/controls.png
sigal/themes/colorbox/static/images/loading.gif
sigal/themes/colorbox/static/js/app-with-media-page.js
sigal/themes/colorbox/static/js/app.js
sigal/themes/colorbox/static/js/jquery-2.2.1.js
sigal/themes/colorbox/static/js/jquery-2.2.1.min.js
sigal/themes/colorbox/static/js/jquery.colorbox-min.js
sigal/themes/colorbox/static/js/jquery.colorbox.js
sigal/themes/colorbox/static/js/jquery.touchSwipe.js
sigal/themes/colorbox/static/js/jquery.touchSwipe.min.js
sigal/themes/colorbox/templates/album.html
sigal/themes/colorbox/templates/album_list.html
sigal/themes/colorbox/templates/base.html
sigal/themes/colorbox/templates/media.html
sigal/themes/default/static/leaflet/Control.FullScreen.css
sigal/themes/default/static/leaflet/Control.FullScreen.js
sigal/themes/default/static/leaflet/Leaflet.Photo.css
sigal/themes/default/static/leaflet/Leaflet.Photo.js
sigal/themes/default/static/leaflet/MarkerCluster.Default.css
sigal/themes/default/static/leaflet/MarkerCluster.css
sigal/themes/default/static/leaflet/README
sigal-2.5.dist-info/LICENSE
sigal-2.5.dist-info/METADATA
sigal-2.5.dist-info/WHEEL
sigal-2.5.dist-info/entry_points.txt
sigal-2.5.dist-info/top_level.txt
sigal-2.5.dist-info/RECORD
