Metadata-Version: 2.2
Name: sigal
Version: 2.5
Summary: Simple static gallery generator
Author-email: Simon Conseil <contact@saimon.org>
License: MIT License
Project-URL: repository, https://github.com/saimn/sigal
Project-URL: documentation, http://sigal.saimon.org/en/latest/
Keywords: gallery,static,generator,image,video,galleria
Classifier: Development Status :: 5 - Production/Stable
Classifier: Environment :: Console
Classifier: License :: OSI Approved :: MIT License
Classifier: Operating System :: OS Independent
Classifier: Programming Language :: Python :: 3
Classifier: Topic :: Internet :: WWW/HTTP
Classifier: Topic :: Multimedia :: Graphics :: Viewers
Classifier: Topic :: Software Development :: Libraries :: Python Modules
Requires-Python: >=3.9
License-File: LICENSE
Requires-Dist: blinker
Requires-Dist: click
Requires-Dist: Jinja2>=2.7
Requires-Dist: Markdown
Requires-Dist: Pillow>=8.0.0
Requires-Dist: pilkit
Requires-Dist: natsort
Provides-Extra: all
Requires-Dist: brotli; extra == "all"
Requires-Dist: feedgenerator; extra == "all"
Requires-Dist: zopfli; extra == "all"
Requires-Dist: cryptography; extra == "all"
Requires-Dist: pillow-heif; extra == "all"
Provides-Extra: tests
Requires-Dist: pytest; extra == "tests"
Requires-Dist: pytest-cov; extra == "tests"
Provides-Extra: docs
Requires-Dist: Sphinx>=4.1.0; extra == "docs"
Requires-Dist: furo; extra == "docs"
Requires-Dist: cryptography; extra == "docs"
